{
	"questions": {
		"question": [
			{
				"type": "radio",
				"title": "¿Cuál es la cifra de las unidades de millar en el número 19.637?",
				"option": [
					"1",
					"9",
					"6"
				],
				"answer": "9",
				"_id": "pregunta_01"
			},
			{
				"type": "radio",
				"title": "¿Cúal es la descomposición del número 30.009 en forma de suma?",
				"option": [
					"3.000 + 9",
					"3.00 + 90",
					"30.000 + 9"
				],
				"answer": "30.000 + 9",
				"_id": "pregunta_02"
			},
			{
				"type": "text",
				"title": "El libro de Alfredo tiene 170 páginas y el de Anita, 215 páginas.\n    ¿Cuántas páginas tienen los dos?",
				"answer": "385",
				"_id": "pregunta_03"
			},
			{
				"type": "checkbox",
				"title": "Selecciona los números par",
				"option": [
					"1",
					"3",
					"4",
					"6",
					"10",
					"15",
					"20",
					"22"
				],
				"answer": [
					"4",
					"6",
					"10",
					"20",
					"22"
				],
				"_id": "pregunta_04"
			},
			{
				"type": "select",
				"title": "¿Cómo se escribe el número cincuenta y tres mil doce?",
				"option": [
					"53.012",
					"53.112",
					"50.012"
				],
				"answer": "53.012",
				"_id": "pregunta_05"
			},
			{
				"type": "datalist",
				"title": "La decena más próxima al número 287 es:",
				"option": [
					"280",
					"300",
					"290"
				],
				"answer": "290",
				"_id": "pregunta_06"
			},
			{
				"type": "text",
				"title": "Perla tiene 59 gallinas. Si nacen en el corral 9 unidades y 2 decenas de pollitos.\n    ¿Cuántas aves tiene en total?",
				"answer": "88",
				"_id": "pregunta_07"
			},
			{
				"type": "text",
				"title": "El álbum de Ricky tiene 180 figuritas, pega 85 figuritas.\n    ¿Cuántas figuritas le falta pegar?",
				"answer": "95",
				"_id": "pregunta_08"
			},
			{
				"type": "radio",
				"title": "El número posterior a 69.190 es:",
				"option": [
					"69.189",
					"69.199",
					"69.191"
				],
				"answer": "69.191",
				"_id": "pregunta_09"
			},
			{
				"type": "radio",
				"title": "¿A qué número corresponde la descomposición 5 DM, 8 UM, 7 C y 1 U?",
				"option": [
					"58.710",
					"58.071",
					"58.701"
				],
				"answer": "58.701",
				"_id": "pregunta_10"
			}
		]
	}
}
